tap_appsflyer/__init__.py
tap_appsflyer/schemas/raw_data/in_app_events.json
tap_appsflyer/schemas/raw_data/installations.json
tap_appsflyer/schemas/raw_data/organic_installs.json
singer_tap_appsflyer-0.0.2.dist-info/LICENSE
singer_tap_appsflyer-0.0.2.dist-info/METADATA
singer_tap_appsflyer-0.0.2.dist-info/WHEEL
singer_tap_appsflyer-0.0.2.dist-info/entry_points.txt
singer_tap_appsflyer-0.0.2.dist-info/top_level.txt
singer_tap_appsflyer-0.0.2.dist-info/RECORD
